learners/__init__.py
learners/learner.py
learners/main.py
learners/utilities.py
learners/visualizer.py
learners/wrangler.py
mlo-0.0.5.dist-info/METADATA
mlo-0.0.5.dist-info/WHEEL
mlo-0.0.5.dist-info/entry_points.txt
mlo-0.0.5.dist-info/top_level.txt
mlo-0.0.5.dist-info/RECORD
