Metadata-Version: 2.1
Name: mlo
Version: 0.0.5
Summary: Object-oriented learners for machine learning
Author: Amine Laghaout
Project-URL: Homepage, https://github.com/laghaout/learners
Requires-Python: >=3.9
